allude/__init__.py
allude/base.py
allude/util.py
allude/examples/__init__.py
allude/examples/gantt.py
allude/examples/sequence_diagram.py
allude-0.1.3.dist-info/LICENSE
allude-0.1.3.dist-info/METADATA
allude-0.1.3.dist-info/WHEEL
allude-0.1.3.dist-info/top_level.txt
allude-0.1.3.dist-info/RECORD
