Metadata-Version: 2.1
Name: allude
Version: 0.1.3
Summary: Building precise functionality from vague specifications
Home-page: https://github.com/i2mint/allude
Author: OtoSense
License: apache-2.0
Platform: any
License-File: LICENSE
Requires-Dist: i2
Requires-Dist: lined
Requires-Dist: meshed
Requires-Dist: graphviz
Requires-Dist: pydot
